mixmasta/__init__.py
mixmasta/cli.py
mixmasta/download.py
mixmasta/mixmasta.py
mixmasta/spacetag_schema.py
mixmasta/data/iso_lookup.csv
mixmasta-0.6.9.dist-info/AUTHORS.md
mixmasta-0.6.9.dist-info/LICENSE
mixmasta-0.6.9.dist-info/METADATA
mixmasta-0.6.9.dist-info/WHEEL
mixmasta-0.6.9.dist-info/entry_points.txt
mixmasta-0.6.9.dist-info/top_level.txt
mixmasta-0.6.9.dist-info/RECORD
