Metadata-Version: 2.1
Name: mixmasta
Version: 0.6.9
Summary: A library for common scientific model transforms
Home-page: https://github.com/jataware/mixmasta
Author: Brandon Rose
Author-email: brandon@jataware.com
License: MIT license
Keywords: mixmasta
Platform: UNKNOWN
Classifier: Development Status :: 2 - Pre-Alpha
Classifier: Intended Audience :: Developers
Classifier: License :: OSI Approved :: MIT License
Classifier: Natural Language :: English
Classifier: Programming Language :: Python :: 3
Classifier: Programming Language :: Python :: 3.5
Classifier: Programming Language :: Python :: 3.6
Classifier: Programming Language :: Python :: 3.7
Classifier: Programming Language :: Python :: 3.8
Requires-Python: >=3.5
License-File: LICENSE
License-File: AUTHORS.md
Requires-Dist: bump2version (==1.0.1)
Requires-Dist: Click (<8,>=7.0)
Requires-Dist: coverage (==4.5.4)
Requires-Dist: Cython (==0.29.23)
Requires-Dist: flake8 (==3.7.8)
Requires-Dist: fuzzywuzzy (>=0.18.0)
Requires-Dist: GDAL (==3.1.4)
Requires-Dist: geofeather (>=0.3.0)
Requires-Dist: geopandas (==0.8.1)
Requires-Dist: netCDF4 (==1.5.3)
Requires-Dist: numpy (==1.22)
Requires-Dist: openpyxl (==3.0.7)
Requires-Dist: pip (>=21.1)
Requires-Dist: pydantic (>=1.8.2)
Requires-Dist: pyproj (==2.6.1.post1)
Requires-Dist: python-Levenshtein (>=0.12.2)
Requires-Dist: rasterio (>=1.1.0)
Requires-Dist: Rtree (==0.8.3)
Requires-Dist: Shapely (==1.7.1)
Requires-Dist: Sphinx (==1.8.5)
Requires-Dist: tox (==3.14.0)
Requires-Dist: tqdm (<5.0.0,>=4.41.1)
Requires-Dist: twine (==1.14.0)
Requires-Dist: watchdog (==0.9.0)
Requires-Dist: wheel (==0.33.6)
Requires-Dist: xarray (==0.16.1)
Requires-Dist: xlrd (==2.0.1)
